deepscan/__init__.py
scdeep/__init__.py
scdeep/dataset.py
scdeep/dca.py
scdeep/deep_impute.py
scdeep/losses.py
scdeep/network.py
scdeep/posterior.py
scdeep/scDeepCluster.py
scdeep/scScope.py
scdeep/trainer.py
scdeep/utils.py
scdeep-0.0.1.dist-info/LICENSE.txt
scdeep-0.0.1.dist-info/METADATA
scdeep-0.0.1.dist-info/WHEEL
scdeep-0.0.1.dist-info/top_level.txt
scdeep-0.0.1.dist-info/RECORD
